rbac_utils_python2/__init__.py
rbac_utils_python2/utils.py
rbac_utils_python2-0.0.1.dist-info/METADATA
rbac_utils_python2-0.0.1.dist-info/WHEEL
rbac_utils_python2-0.0.1.dist-info/top_level.txt
rbac_utils_python2-0.0.1.dist-info/RECORD
