Metadata-Version: 2.1
Name: rbac-utils-python2
Version: 0.0.1
Summary: Utilities for RBAC system
Home-page: UNKNOWN
Author: Sandeep Sharma
Author-email: sandeep.sharma@lendenclub.com
License: UNKNOWN
Platform: UNKNOWN
Requires-Dist: PyJWT (==1.7.1)
Requires-Dist: requests (==2.18.4)
Requires-Dist: python-dotenv (==0.18.0)
